mcframework/__init__.py
mcframework/core.py
mcframework/stats_engine.py
mcframework/utils.py
mcframework/sims/__init__.py
mcframework/sims/black_scholes.py
mcframework/sims/pi.py
mcframework/sims/portfolio.py
mcframework-0.1.0.dist-info/licenses/LICENSE
mcframework-0.1.0.dist-info/METADATA
mcframework-0.1.0.dist-info/WHEEL
mcframework-0.1.0.dist-info/top_level.txt
mcframework-0.1.0.dist-info/RECORD
