Metadata-Version: 2.4
Name: mcframework
Version: 0.1.0
Summary: Lightweight, parallel, and reproducible Monte Carlo simulation framework
Author: Milan Fusco
License-Expression: MIT
Project-URL: Homepage, https://github.com/milanfusco/mcFramework/
Project-URL: Docs, https://milanfusco.github.io/mcFramework/
Classifier: Programming Language :: Python :: 3
Classifier: Operating System :: OS Independent
Requires-Python: >=3.10
License-File: LICENSE
Requires-Dist: numpy>=1.24
Requires-Dist: matplotlib>=3.7
Requires-Dist: scipy>=1.10
Provides-Extra: dev
Requires-Dist: pylint>=3.2; extra == "dev"
Requires-Dist: pylint-exit>=1.2; extra == "dev"
Requires-Dist: ruff>=0.6; extra == "dev"
Provides-Extra: docs
Requires-Dist: sphinx>=7.2; extra == "docs"
Requires-Dist: pydata-sphinx-theme>=0.15; extra == "docs"
Requires-Dist: myst-parser>=2.0; extra == "docs"
Requires-Dist: sphinx-autodoc-typehints>=2.0; extra == "docs"
Requires-Dist: sphinx-copybutton>=0.5; extra == "docs"
Requires-Dist: sphinx-design>=0.6; extra == "docs"
Requires-Dist: sphinxcontrib-mermaid>=0.9; extra == "docs"
Requires-Dist: numpydoc>=1.6; extra == "docs"
Requires-Dist: sphinx-gallery>=0.16; extra == "docs"
Requires-Dist: matplotlib>=3.7; extra == "docs"
Provides-Extra: test
Requires-Dist: pytest>=7.2; extra == "test"
Requires-Dist: pytest-cov>=4.0; extra == "test"
Requires-Dist: coverage>=7.2; extra == "test"
Provides-Extra: gui
Requires-Dist: PySide6>=6.5; extra == "gui"
Requires-Dist: yfinance>=0.2; extra == "gui"
Dynamic: license-file
